nebari_plugin_self_registration/__about__.py
nebari_plugin_self_registration/__init__.py
nebari_plugin_self_registration/terraform/main.tf
nebari_plugin_self_registration/terraform/outputs.tf
nebari_plugin_self_registration/terraform/variables.tf
nebari_plugin_self_registration/terraform/versions.tf
nebari_plugin_self_registration/terraform/modules/keycloak/main.tf
nebari_plugin_self_registration/terraform/modules/keycloak/outputs.tf
nebari_plugin_self_registration/terraform/modules/keycloak/variables.tf
nebari_plugin_self_registration/terraform/modules/keycloak/versions.tf
nebari_plugin_self_registration/terraform/modules/self-registration/main.tf
nebari_plugin_self_registration/terraform/modules/self-registration/outputs.tf
nebari_plugin_self_registration/terraform/modules/self-registration/variables.tf
nebari_plugin_self_registration/terraform/modules/self-registration/chart/.helmignore
nebari_plugin_self_registration/terraform/modules/self-registration/chart/Chart.yaml
nebari_plugin_self_registration/terraform/modules/self-registration/chart/values.yaml
nebari_plugin_self_registration/terraform/modules/self-registration/chart/templates/NOTES.txt
nebari_plugin_self_registration/terraform/modules/self-registration/chart/templates/_helpers.tpl
nebari_plugin_self_registration/terraform/modules/self-registration/chart/templates/deployment.yaml
nebari_plugin_self_registration/terraform/modules/self-registration/chart/templates/hpa.yaml
nebari_plugin_self_registration/terraform/modules/self-registration/chart/templates/ingress.yaml
nebari_plugin_self_registration/terraform/modules/self-registration/chart/templates/job.yaml
nebari_plugin_self_registration/terraform/modules/self-registration/chart/templates/secret.yaml
nebari_plugin_self_registration/terraform/modules/self-registration/chart/templates/service.yaml
nebari_plugin_self_registration/terraform/modules/self-registration/chart/templates/serviceaccount.yaml
nebari_plugin_self_registration-0.0.15.dist-info/METADATA
nebari_plugin_self_registration-0.0.15.dist-info/WHEEL
nebari_plugin_self_registration-0.0.15.dist-info/entry_points.txt
nebari_plugin_self_registration-0.0.15.dist-info/licenses/LICENSE
nebari_plugin_self_registration-0.0.15.dist-info/RECORD
