Metadata-Version: 2.3
Name: nebari-plugin-self-registration
Version: 0.0.15
Summary: MetroStar - Self-Registration Plugin for Nebari Platform
Project-URL: Documentation, https://github.com/MetroStar/nebari-self-registration#readme
Project-URL: Issues, https://github.com/MetroStar/nebari-self-registration/issues
Project-URL: Source, https://github.com/MetroStar/nebari-self-registration
Author-email: Ken Foster <kfoster@metrostar.com>
License-Expression: Apache-2.0
License-File: LICENSE
Classifier: Development Status :: 4 - Beta
Classifier: Programming Language :: Python
Classifier: Programming Language :: Python :: 3.9
Classifier: Programming Language :: Python :: 3.10
Classifier: Programming Language :: Python :: 3.11
Classifier: Programming Language :: Python :: Implementation :: CPython
Classifier: Programming Language :: Python :: Implementation :: PyPy
Requires-Python: >=3.9
Requires-Dist: nebari
